pydvpl/__init__.py
pydvpl/_pydvpl.py
pydvpl/color/__init__.py
pydvpl/color/_color.py
pydvpl/dvpl/__init__.py
pydvpl/dvpl/_dvpl.py
pydvpl/version/__init__.py
pydvpl/version/_version.py
pydvpl-1.2.1.dist-info/METADATA
pydvpl-1.2.1.dist-info/WHEEL
pydvpl-1.2.1.dist-info/entry_points.txt
pydvpl-1.2.1.dist-info/licenses/LICENSE
pydvpl-1.2.1.dist-info/RECORD
