Metadata-Version: 2.3
Name: pydvpl
Version: 1.2.1
Summary: A CLI Tool Coded In Python3 To Convert WoTB ( Dava ) SmartDLC DVPL File Based On LZ4 High Compression.
Project-URL: Homepage, https://github.com/rifsxd/pydvpl
Author-email: RifsxD <support@rxd-mods.xyz>
License: MIT License
License-File: LICENSE
Classifier: Environment :: Console
Classifier: License :: OSI Approved :: MIT License
Classifier: Operating System :: OS Independent
Classifier: Programming Language :: Python :: 3
Requires-Python: >=3.10
Requires-Dist: lz4>=4.3.3
Requires-Dist: packaging>=24.0
Requires-Dist: requests>=2.31.0
